[
{
    "name":             "voltage",
    "shortDescription": "UAVCAN Volt",
    "type":             "float",
    "decimalPlaces":    2,
    "units":            "v"
},
{
    "name":             "lat",
    "shortDescription": "UAVCAN LAT",
    "type":             "double",
    "decimalPlaces":    7
},
{
    "name":             "lon",
    "shortDescription": "UAVCAN LON",
    "type":             "double",
    "decimalPlaces":    7
},
{
    "name":             "ESC",
    "shortDescription": "ESC",
    "type":             "double",
    "decimalPlaces":    1
}
]
